example/__init__.py
example/example.py
example/example2.py
hawkcatcher/__init__.py
hawkcatcher/core.py
hawkcatcher/errors.py
hawkcatcher/types.py
tests/__init__.py
tests/test_cather.py
hawkcatcher-3.4.1.dist-info/LICENSE
hawkcatcher-3.4.1.dist-info/METADATA
hawkcatcher-3.4.1.dist-info/WHEEL
hawkcatcher-3.4.1.dist-info/top_level.txt
hawkcatcher-3.4.1.dist-info/RECORD
