Metadata-Version: 2.1
Name: hawkcatcher
Version: 3.4.1
Summary: Python errors Catcher module for Hawk.
Home-page: https://github.com/codex-team/deployserver
Author: CodeX Team
Author-email: team@ifmo.su
License: MIT
Keywords: catcher hawk codex bug errors tracker
Classifier: Intended Audience :: Developers
Classifier: Topic :: Software Development :: Bug Tracking
Classifier: License :: OSI Approved :: MIT License
Classifier: Programming Language :: Python :: 3.5
Classifier: Environment :: Console
Classifier: Environment :: Web Environment
Requires-Python: >=3.5
License-File: LICENSE
Requires-Dist: requests
